qr.py
qrtunnel-3.2.0.dist-info/METADATA
qrtunnel-3.2.0.dist-info/WHEEL
qrtunnel-3.2.0.dist-info/entry_points.txt
qrtunnel-3.2.0.dist-info/top_level.txt
qrtunnel-3.2.0.dist-info/RECORD
