Metadata-Version: 2.4
Name: qrtunnel
Version: 3.2.0
Summary: Cross-platform file sharing via QR code. Defaults to account-free SSH tunneling on Linux/macOS.
Author-email: Aniruth Karthik <aniruthkarthik10@gmail.com>
License-Expression: MIT
Classifier: Programming Language :: Python :: 3
Classifier: Programming Language :: Python :: 3.6
Classifier: Programming Language :: Python :: 3.7
Classifier: Programming Language :: Python :: 3.8
Classifier: Programming Language :: Python :: 3.9
Classifier: Programming Language :: Python :: 3.10
Classifier: Programming Language :: Python :: 3.11
Classifier: Operating System :: OS Independent
Requires-Python: >=3.6
Requires-Dist: qrcode
Requires-Dist: pyngrok
Requires-Dist: streaming-form-data
Requires-Dist: werkzeug
